rtslib/__init__.py
rtslib/alua.py
rtslib/fabric.py
rtslib/node.py
rtslib/root.py
rtslib/target.py
rtslib/targetctl.py
rtslib/tcm.py
rtslib/utils.py
rtslib_fb.py
rtslib_fb-2.2.3.dist-info/METADATA
rtslib_fb-2.2.3.dist-info/WHEEL
rtslib_fb-2.2.3.dist-info/entry_points.txt
rtslib_fb-2.2.3.dist-info/licenses/COPYING
rtslib_fb-2.2.3.dist-info/RECORD
