Metadata-Version: 2.4
Name: rtslib-fb
Version: 2.2.3
Summary: API for Linux kernel SCSI target (aka LIO)
Project-URL: Homepage, http://github.com/open-iscsi/rtslib-fb
Author-email: Andy Grover <agrover@redhat.com>, Jerome Martin <jxm@risingtidesystems.com>
Maintainer-email: Maurizio Lombardi <mlombard@redhat.com>
License-Expression: Apache-2.0
License-File: COPYING
Classifier: License :: OSI Approved :: Apache Software License
Classifier: Operating System :: POSIX :: Linux
Classifier: Programming Language :: Python :: 3
Classifier: Programming Language :: Python :: 3.9
Classifier: Programming Language :: Python :: 3.12
Requires-Python: >=3.9
Requires-Dist: pyudev~=0.18
